{"cameraMode":{"drawMode":0,"name":"Shaded","section":"Shading Mode"},"sceneLighting":true,"audioPlay":false,"sceneViewState":{"m_AlwaysRefresh":false,"showFog":true,"showSkybox":true,"showFlares":true,"showImageEffects":true,"showParticleSystems":true,"showVisualEffectGraphs":true,"m_FxEnabled":true},"in2DMode":false,"pivot":{"x":10.42821979522705,"y":1.156233549118042,"z":8.085183143615723},"rotation":{"x":0.17644496262073518,"y":0.7704815864562988,"z":-0.24137632548809052,"w":0.5631377696990967},"size":0.7914788722991943,"orthographic":false}